gllm_plugin/__init__.pyi
gllm_plugin/config/__init__.pyi
gllm_plugin/config/app_config.pyi
gllm_plugin/config/constant.pyi
gllm_plugin/pipeline/__init__.pyi
gllm_plugin/pipeline/base_pipeline_preset_config.pyi
gllm_plugin/pipeline/pipeline_handler.pyi
gllm_plugin/pipeline/pipeline_plugin.pyi
gllm_plugin/storage/__init__.pyi
gllm_plugin/storage/base_anonymizer_storage.pyi
gllm_plugin/storage/base_chat_history_storage.pyi
gllm_plugin/tools/__init__.pyi
gllm_plugin/tools/decorators.pyi
gllm_plugin.build/.gitignore
gllm_plugin.cpython-312-darwin.so
gllm_plugin.pyi
gllm_plugin_binary-0.1.10.dist-info/METADATA
gllm_plugin_binary-0.1.10.dist-info/WHEEL
gllm_plugin_binary-0.1.10.dist-info/RECORD
