Metadata-Version: 2.1
Name: gllm-plugin-binary
Version: 0.1.10
Summary: 
Author: GenAI SDK Team
Author-email: gat-sdk@gdplabs.id
Requires-Python: >=3.11,<3.13
Classifier: Programming Language :: Python :: 3
Classifier: Programming Language :: Python :: 3.11
Classifier: Programming Language :: Python :: 3.12
Provides-Extra: flair
Requires-Dist: bosa-core-binary (>=0.5.0,<0.6.0)
Requires-Dist: gllm-core-binary (>=0.3.0,<0.4.0)
Requires-Dist: gllm-inference-binary (>=0.4.0,<0.5.0)
Requires-Dist: gllm-pipeline-binary (>=0.4.0,<0.5.0)
Requires-Dist: langchain (>=0.3.0,<0.4.0)
Requires-Dist: langchain-core (>=0.3.0,<0.4.0)
Requires-Dist: poetry (>=2.1.3,<3.0.0)
Requires-Dist: semver (>=3.0.4,<4.0.0)
